{"timestamp": "2026-02-15T22:00:00.316444-01:00", "greenhouse": {"timestamp": "2026-02-15 21:58:06", "temp": 18.3, "humidity": 81.1, "vpd": 0.397, "dew_point": 15.0}, "outdoor": {"timestamp": "2026-02-15 21:38:57", "temp": 16.0, "humidity": 75.9, "vpd": 0.438, "dew_point": 11.75}, "miflora": {"first": {"temperature_c": 19.1, "illuminance_lux": 111, "moisture_pct": 57, "conductivity_us_cm": 814}, "second": {"temperature_c": 19.3, "illuminance_lux": 107, "moisture_pct": 43, "conductivity_us_cm": 247}}}