{"timestamp": "2026-03-06T08:00:00.231012-01:00", "greenhouse": {"timestamp": "2026-03-06 07:54:05", "temp": 17.9, "humidity": 71.0, "vpd": 0.595, "dew_point": 12.56}, "outdoor": {"timestamp": "2026-03-03 13:46:01", "temp": 16.4, "humidity": 74.2, "vpd": 0.481, "dew_point": 11.79}, "miflora": {"first": {"temperature_c": 20.0, "illuminance_lux": 329, "moisture_pct": 10, "conductivity_us_cm": 12}, "second": {"temperature_c": 18.0, "illuminance_lux": 355, "moisture_pct": 21, "conductivity_us_cm": 113}}}