{"timestamp": "2026-02-07T03:00:00.244755-01:00", "greenhouse": {"timestamp": "2026-02-07 02:55:05", "temp": 18.1, "humidity": 83.1, "vpd": 0.351, "dew_point": 15.18}, "outdoor": {"timestamp": "2026-02-07 01:11:02", "temp": 14.5, "humidity": 83.6, "vpd": 0.271, "dew_point": 11.75}, "miflora": {"first": {"temperature_c": 18.3, "illuminance_lux": 101, "moisture_pct": 49, "conductivity_us_cm": 823}, "second": {"temperature_c": 18.5, "illuminance_lux": 96, "moisture_pct": 44, "conductivity_us_cm": 280}}}